wow_world_messages/__init__.py
wow_world_messages/tbc.py
wow_world_messages/util.py
wow_world_messages/vanilla.py
wow_world_messages/wrath.py
wow_world_messages-0.1.0.dist-info/METADATA
wow_world_messages-0.1.0.dist-info/WHEEL
wow_world_messages-0.1.0.dist-info/top_level.txt
wow_world_messages-0.1.0.dist-info/RECORD
